{"lint_capabilities":{"enabled":true,"tier":"core","owner":"platform","capabilities":["contracts"]},"lint_contract":{"enabled":true,"tier":"core","owner":"platform","capabilities":["contracts"]},"lint_events":{"enabled":true,"tier":"core","owner":"platform","capabilities":["events_unified"]},"lint_failure":{"enabled":true,"tier":"core","owner":"platform","capabilities":["resilience_layer"]},"lint_feature_flags":{"enabled":true,"tier":"core","owner":"platform","capabilities":["resilience_layer"]},"lint_formatter":{"enabled":true,"tier":"core","owner":"platform","capabilities":["formatting","events_unified"]},"lint_health":{"enabled":true,"tier":"core","owner":"platform","capabilities":["health_checks"]},"lint_registry":{"enabled":true,"tier":"core","owner":"platform","capabilities":[]},"lint_snapshots":{"enabled":true,"tier":"core","owner":"platform","capabilities":["snapshots"]},"nox_sessions.lint":{"enabled":true,"tier":"core","owner":"platform","capabilities":["resilience_layer","lint_all_quiet_retry","snapshots"]}}
